LICENSE.txt
MANIFEST.in
README.md
setup.cfg
setup.py
django_era.egg-info/PKG-INFO
django_era.egg-info/SOURCES.txt
django_era.egg-info/dependency_links.txt
django_era.egg-info/requires.txt
django_era.egg-info/top_level.txt
era/__init__.py
era/components.py
era/forms.py
era/settings.py
era/urls.py
era/apps/__init__.py
era/apps/user/__init__.py
era/apps/user/communicators.py
era/apps/user/components.py
era/apps/user/decorators.py
era/apps/user/mixins.py
era/apps/user/models.py
era/apps/user/settings.py
era/apps/user/urls.py
era/apps/user/views.py
era/apps/user/locale/ru/LC_MESSAGES/django.mo
era/apps/user/locale/ru/LC_MESSAGES/django.po
era/management/__init__.py
era/management/commands/__init__.py
era/management/commands/flush.py
era/static/scripts/era.js
era/static/styles/era.css
era/static/widgets/slider.js
era/templates/base.html
era/templates/errors.html
era/templatetags/__init__.py
era/templatetags/forms.py
era/templatetags/library.py
era/templatetags/lists.py
era/templatetags/markup.py
era/templatetags/media.py
era/templatetags/menu.py
era/tests/__init__.py
era/tests/base.py
era/tests/runner.py
era/tests/test_functools.py
era/utils/__init__.py
era/utils/functools.py
era/utils/urls.py
era/utils/translation/__init__.py
era/utils/translation/ru.py
era/utils/translation/string.py
era/utils/translation/verbose.py
era/views/__init__.py
era/views/base.py
era/views/forms.py
era/views/lists.py