Metadata-Version: 1.1
Name: django-era
Version: 1.5.2
Summary: django app that introduces some architectural solutions
Home-page: https://github.com/doctorzeb8/django-era
Author: doctorzeb8
Author-email: doctorzeb8@gmail.com
License: MIT
Keywords: django framework cbv components react
Platform: UNKNOWN
Classifier: License :: OSI Approved :: MIT License
Classifier: Development Status :: 3 - Alpha
Classifier: Environment :: Web Environment
Classifier: Programming Language :: Python :: 3
Classifier: Programming Language :: Python :: 3.2
Classifier: Programming Language :: Python :: 3.3
Classifier: Programming Language :: Python :: 3.4
Classifier: Framework :: Django
